contexta_core-0.1.4.dist-info/METADATA
contexta_core-0.1.4.dist-info/WHEEL
contexta_core/__init__.py
contexta_core/_bindings.pyd
contexta_core/py.typed
contexta_core-0.1.4.dist-info/RECORD
