Metadata-Version: 2.4
Name: contexta-core
Version: 0.1.4
Classifier: Development Status :: 4 - Beta
Classifier: Intended Audience :: Developers
Classifier: License :: OSI Approved :: Apache Software License
Classifier: License :: OSI Approved :: MIT License
Classifier: Programming Language :: Python :: 3
Classifier: Programming Language :: Python :: 3.8
Classifier: Programming Language :: Python :: 3.9
Classifier: Programming Language :: Python :: 3.10
Classifier: Programming Language :: Python :: 3.11
Classifier: Programming Language :: Python :: 3.12
Classifier: Programming Language :: Rust
Summary: Contexta code analysis core engine
Keywords: code-analysis,tree-sitter,static-analysis,mcp
Author-email: Contexta Team <team@contexta.dev>
License: Apache-2.0 OR MIT
Requires-Python: >=3.8
